{
  "advancements": [
    {
      "conditions": [
        {
          "flag": "aesthetics_enabled",
          "type": "simpleores:flag"
        }
      ],
      "advancement": {
        "parent": "minecraft:recipes/root",
        "rewards": {
          "recipes": [
            "simpleores:adamantium_door"
          ]
        },
        "criteria": {
          "has_item": {
            "trigger": "minecraft:inventory_changed",
            "conditions": {
              "items": [
                {
                  "items": [
                    "simpleores:adamantium_ingot"
                  ]
                }
              ]
            }
          }
        },
        "requirements": [
          [
            "has_item"
          ]
        ]
      }
    }
  ]
}