{
  "type": "minecraft:chest",
  "pools": [
    {
      "name": "main",
      "rolls": {
        "type": "minecraft:uniform",
        "min": 1.0,
        "max": 1.0
      },
      "bonus_rolls": 0.0,
      "entries": [
        {
          "type": "minecraft:item",
          "name": "simpleores:onyx_helmet"
        },
        {
          "type": "minecraft:item",
          "name": "simpleores:onyx_chestplate"
        },
        {
          "type": "minecraft:item",
          "name": "simpleores:onyx_leggings"
        },
        {
          "type": "minecraft:item",
          "name": "simpleores:onyx_boots"
        },
        {
          "type": "minecraft:item",
          "name": "simpleores:onyx_sword"
        },
        {
          "type": "minecraft:item",
          "name": "simpleores:onyx_axe"
        },
        {
          "type": "minecraft:item",
          "name": "simpleores:onyx_pickaxe"
        },
        {
          "type": "minecraft:item",
          "name": "simpleores:onyx_shovel"
        },
        {
          "type": "minecraft:item",
          "name": "simpleores:onyx_bow"
        },
        {
          "type": "minecraft:item",
          "name": "simpleores:onyx_shears"
        },
        {
          "type": "minecraft:item",
          "weight": 3,
          "functions": [
            {
              "function": "minecraft:set_count",
              "count": {
                "type": "minecraft:uniform",
                "min": 2.0,
                "max": 4.0
              },
              "add": false
            }
          ],
          "name": "simpleores:onyx_gem"
        }
      ],
      "conditions": [
        {
          "condition": "minecraft:random_chance",
          "chance": 0.25
        }
      ]
    }
  ]
}